{
	"name": "CodeBlockShadow",
	"plugin-id": "NinePatch",
	"sid": 420265912342333,
	"isGlobal": false,
	"instanceVariables": [
		{
			"name": "level",
			"type": "number",
			"desc": "",
			"show": true,
			"sid": 940736574568507
		},
		{
			"name": "addToGrandParent",
			"type": "boolean",
			"desc": "",
			"show": true,
			"sid": 976884799844236
		},
		{
			"name": "shouldShift",
			"type": "boolean",
			"desc": "",
			"show": true,
			"sid": 968839894719661
		},
		{
			"name": "relativeLevelToParent",
			"type": "number",
			"desc": "",
			"show": true,
			"sid": 633144977237466
		}
	],
	"behaviorTypes": [],
	"effectTypes": [],
	"image": {
		"width": 96,
		"height": 96,
		"originX": 0.5,
		"originY": 0.5,
		"originalSource": "",
		"exportFormat": "lossless",
		"exportQuality": 0.8,
		"imageSpriteId": 7495651,
		"useCollisionPoly": true
	}
}